ds_stoa/__init__.py
ds_stoa/authentication/__init__.py
ds_stoa/authentication/_oauth2.py
ds_stoa/authentication/_rest.py
ds_stoa/fetch/__init__.py
ds_stoa/fetch/_fetch.py
ds_stoa/manager/__init__.py
ds_stoa/manager/client.py
ds_stoa/order/__init__.py
ds_stoa/order/_order.py
ds_stoa/sign/__init__.py
ds_stoa/sign/_sign.py
ds_stoa/utils/__init__.py
ds_stoa/utils/decorators/__init__.py
ds_stoa/utils/decorators/authentication.py
ds_stoa/utils/exceptions/__init__.py
ds_stoa/utils/exceptions/_handler.py
ds_stoa/utils/logger/__init__.py
ds_stoa/utils/logger/_context.py
ds_stoa/utils/logger/_logger.py
ds_stoa-0.2.1.dist-info/LICENCE
ds_stoa-0.2.1.dist-info/METADATA
ds_stoa-0.2.1.dist-info/WHEEL
ds_stoa-0.2.1.dist-info/top_level.txt
ds_stoa-0.2.1.dist-info/RECORD
