Metadata-Version: 2.1
Name: ds-stoa
Version: 0.2.1
Summary: A python package for GraspDP Stoa. Simple and easy way to interact with GraspDP datalake.
Author-email: Kristoffer Varslott <kristoffer@grasplabs.no>
Maintainer-email: Kristoffer Varslott <kristoffer@grasplabs.no>
License: MIT License
Project-URL: Homepage, https://graspdp.com/
Project-URL: Documentation, https://grasp-labs.github.io/ds-stoa/
Project-URL: Repository, https://github.com/grasp-labs/ds-stoa/
Project-URL: Issues, https://github.com/grasp-labs/ds-stoa/issues/
Project-URL: Changelog, https://github.com/grasp-labs/ds-stoa/blob/main/CHANGELOG.md
Keywords: grasp-labs,python
Classifier: Development Status :: 4 - Beta
Classifier: Programming Language :: Python
Classifier: License :: OSI Approved :: MIT License
Classifier: Operating System :: OS Independent
Requires-Python: >=3.8
License-File: LICENCE
Requires-Dist: pandas
Requires-Dist: requests
Requires-Dist: pyarrow
